halig-0.6.1.dist-info/METADATA
halig-0.6.1.dist-info/WHEEL
halig-0.6.1.dist-info/entry_points.txt
halig-0.6.1.dist-info/licenses/LICENSE
halig/__init__.py
halig/__version__.py
halig/commands/__init__.py
halig/commands/base.py
halig/commands/edit.py
halig/commands/git/__init__.py
halig/commands/git/base.py
halig/commands/git/commit.py
halig/commands/git/pull.py
halig/commands/git/push.py
halig/commands/git/status.py
halig/commands/import_unencrypted.py
halig/commands/notebooks.py
halig/commands/reencrypt.py
halig/commands/search.py
halig/commands/show.py
halig/encryption.py
halig/literals.py
halig/main.py
halig/settings.py
halig/utils.py
halig-0.6.1.dist-info/RECORD
