Metadata-Version: 2.1
Name: halig
Version: 0.6.1
Summary: age-encrypted, file-based, note-taking CLI app
Keywords: cli,notes,age,rage,encryption,notebook
Author-Email: =?utf-8?b?Y8SDdMSDbGlu?= <185504a9@duck.com>
License: GPL-3.0-or-later
Classifier: Development Status :: 4 - Beta
Classifier: Environment :: Console
Classifier: License :: OSI Approved :: GNU General Public License v3 or later (GPLv3+)
Classifier: Natural Language :: English
Classifier: Operating System :: POSIX :: Linux
Classifier: Programming Language :: Python :: 3.10
Classifier: Programming Language :: Python :: 3.11
Classifier: Programming Language :: Python :: 3.12
Classifier: Topic :: Terminals
Classifier: Topic :: Utilities
Classifier: Typing :: Typed
Project-URL: Homepage, https://git.roboces.dev/catalin/halig
Project-URL: Repository, https://git.roboces.dev/catalin/halig
Project-URL: Documentation, https://git.roboces.dev/catalin/halig
Project-URL: Changelog, https://git.roboces.dev/catalin/halig
Requires-Python: >=3.10
Requires-Dist: typer>=0
Requires-Dist: rich>=13.8
Requires-Dist: pydantic>=2.8
Requires-Dist: pyyaml>=6.0
Requires-Dist: pyrage>=1
Requires-Dist: httpx>=0
Requires-Dist: platformdirs>=4.2
Requires-Dist: pydantic-settings>=2
Requires-Dist: hishel>=0
Requires-Dist: whenever>=0.6
Requires-Dist: gitpython>=3.1
Requires-Dist: pytest>=7; extra == "testing"
Requires-Dist: pytest-cov>=4; extra == "testing"
Requires-Dist: pyfakefs>=5; extra == "testing"
Requires-Dist: pytest-clarity>=1; extra == "testing"
Requires-Dist: pytest-reportlog>=0; extra == "testing"
Requires-Dist: pytest-duration-insights>=0; extra == "testing"
Requires-Dist: pytest-pretty>=1; extra == "testing"
Requires-Dist: pytest-mock>=3; extra == "testing"
Requires-Dist: mock>=5; extra == "testing"
Requires-Dist: faker>=28.1.0; extra == "testing"
Requires-Dist: ruff>=0.4; extra == "linting"
Requires-Dist: pyright>=1.1; extra == "linting"
Requires-Dist: mypy>=1.1; extra == "linting"
Requires-Dist: types-PyYAML>=6.0; extra == "linting"
Requires-Dist: mkdocs-material>=9.1.5; extra == "docs"
Requires-Dist: mkdocstrings[python]>=0.20.0; extra == "docs"
Requires-Dist: bump-pydantic>=0.6.0; extra == "dev"
Provides-Extra: testing
Provides-Extra: linting
Provides-Extra: docs
Provides-Extra: dev
